Workbook

Sheet Precios
A1: Categoría | B1: Ítem | C1: Precio unitario | D1: Unidad
A2: Producción | B2: Producción ejecutiva | C2: 150000 | D2: GLB
A3: Producción | B3: Coordinación general | C3: 120000 | D3: GLB
A4: Técnica | B4: Sonido / PA | C4: 130000 | D4: GLB
A5: Técnica | B5: Iluminación | C5: 110000 | D5: GLB
A6: Técnica | B6: Video y pantallas | C6: 200000 | D6: GLB
A7: Técnica | B7: Montaje y décor adaptable | C7: 180000 | D7: GLB
A8: Técnica | B8: Vestuario/imagen pública | C8: 100000 | D8: GLB
A9: Espacio | B9: Alquiler de espacio | C9: 900000 | D9: GLB
A10: Espacio | B10: Montaje y desmontaje | C10: 250000 | D10: GLB
A11: Espacio | B11: Permisos/seguros | C11: 120000 | D11: GLB
A12: Difusión | B12: Fotografía/registro | C12: 120000 | D12: GLB
A13: Difusión | B13: Diseño gráfico/RRSS | C13: 140000 | D13: GLB
... A20: Fondo | B20: Imprevistos (10%) | C20: 200000 | D20: GLB

Sheet Presupuesto
A1: Categoría | B1: Ítem | C1: Unidad | D1: Precio ref. | E1: Cantidad | F1: Subtotal | G1: Nota
A2: Producción | B2: Producción ejecutiva | C2: GLB | D2: =VLOOKUP(B2,Precios!$B$1:$C$20,2,FALSE) -> 0 | E2: 0 | F2: =D2*E2 -> 0
A3: Producción | B3: Coordinación general | C3: GLB | D3: =VLOOKUP(B3,Precios!$B$1:$C$20,2,FALSE) -> 0 | E3: 0 | F3: =D3*E3 -> 0
A4: Técnica | B4: Sonido / PA | C4: GLB | D4: =VLOOKUP(B4,Precios!$B$1:$C$20,2,FALSE) -> 0 | E4: 0 | F4: =D4*E4 -> 0
A5: Técnica | B5: Iluminación | C5: GLB | D5: =VLOOKUP(B5,Precios!$B$1:$C$20,2,FALSE) -> 0 | E5: 0 | F5: =D5*E5 -> 0
A6: Técnica | B6: Video y pantallas | C6: GLB | D6: =VLOOKUP(B6,Precios!$B$1:$C$20,2,FALSE) -> 0 | E6: 0 | F6: =D6*E6 -> 0
A7: Técnica | B7: Montaje y décor adaptable | C7: GLB | D7: =VLOOKUP(B7,Precios!$B$1:$C$20,2,FALSE) -> 0 | E7: 0 | F7: =D7*E7 -> 0
A8: Técnica | B8: Vestuario/imagen pública | C8: GLB | D8: =VLOOKUP(B8,Precios!$B$1:$C$20,2,FALSE) -> 0 | E8: 0 | F8: =D8*E8 -> 0
A9: Espacio | B9: Alquiler de espacio | C9: GLB | D9: =VLOOKUP(B9,Precios!$B$1:$C$20,2,FALSE) -> 0 | E9: 0 | F9: =D9*E9 -> 0
A10: Espacio | B10: Montaje y desmontaje | C10: GLB | D10: =VLOOKUP(B10,Precios!$B$1:$C$20,2,FALSE) -> 0 | E10: 0 | F10: =D10*E10 -> 0
A11: Espacio | B11: Permisos/seguros | C11: GLB | D11: =VLOOKUP(B11,Precios!$B$1:$C$20,2,FALSE) -> 0 | E11: 0 | F11: =D11*E11 -> 0
A12: Difusión | B12: Fotografía/registro | C12: GLB | D12: =VLOOKUP(B12,Precios!$B$1:$C$20,2,FALSE) -> 0 | E12: 0 | F12: =D12*E12 -> 0
A13: Difusión | B13: Diseño gráfico/RRSS | C13: GLB | D13: =VLOOKUP(B13,Precios!$B$1:$C$20,2,FALSE) -> 0 | E13: 0 | F13: =D13*E13 -> 0
... A20: Fondo | B20: Imprevistos (10%) | C20: GLB | D20: =VLOOKUP(B20,Precios!$B$1:$C$20,2,FALSE) -> 0 | E20: 0 | F20: =D20*E20 -> 0

Sheet Resumen
A1: Categoría | B1: Subtotal
A2: Administrativo | B2: =SUMIF(Presupuesto!$A:$A,A2,Presupuesto!$F:$F) -> 0
A3: Difusión | B3: =SUMIF(Presupuesto!$A:$A,A3,Presupuesto!$F:$F) -> 0
A4: Espacio | B4: =SUMIF(Presupuesto!$A:$A,A4,Presupuesto!$F:$F) -> 0
A5: Fondo | B5: =SUMIF(Presupuesto!$A:$A,A5,Presupuesto!$F:$F) -> 0
A6: Producción | B6: =SUMIF(Presupuesto!$A:$A,A6,Presupuesto!$F:$F) -> 0
A7: Técnica | B7: =SUMIF(Presupuesto!$A:$A,A7,Presupuesto!$F:$F) -> 0
